README.md
setup.py
TOPSIS_Ajat_101803268/__init__.py
TOPSIS_Ajat_101803268/topsis.py
TOPSIS_Ajat_101803268.egg-info/PKG-INFO
TOPSIS_Ajat_101803268.egg-info/SOURCES.txt
TOPSIS_Ajat_101803268.egg-info/dependency_links.txt
TOPSIS_Ajat_101803268.egg-info/requires.txt
TOPSIS_Ajat_101803268.egg-info/top_level.txt