Metadata-Version: 2.1
Name: TOPSIS-Ajat-101803268
Version: 0.1
Summary: A python package for Multiple Criteria Decision Making (MCDM) using Topsis
Home-page: https://github.com/Ajat-beep/TOPSIS_Ajat_101803268
Author: Ajat Suneja
Author-email: sunejaajat71@gmail.com
License: MIT
Download-URL: https://github.com/Ajat-beep/TOPSIS_Ajat_101803268/archive/0.1.tar.gz
Keywords: TOPSIS
Platform: UNKNOWN
Classifier: Development Status :: 3 - Alpha
Classifier: Intended Audience :: Developers
Classifier: Topic :: Software Development :: Build Tools
Classifier: License :: OSI Approved :: MIT License
Classifier: Programming Language :: Python :: 3
Classifier: Programming Language :: Python :: 3.4
Classifier: Programming Language :: Python :: 3.5
Classifier: Programming Language :: Python :: 3.6
Classifier: Programming Language :: Python :: 3.7
Classifier: Programming Language :: Python :: 3.8
